Metadata-Version: 1.1
Name: bob.paper.lipsync2019
Version: 1.0.0
Summary: Source code for EUSIPCO 2018 paper on audio-visual inconsistency detection
Home-page: https://gitlab.idiap.ch/bob/bob.paper.lipsync2019
Author: Pavel Korshunov
Author-email: pavel.korshunov@idiap.ch
License: BSD
Keywords: paper at ICML workshop 2019,audio-visual inconsistency
Platform: UNKNOWN
Classifier: Framework :: Bob
Classifier: Development Status :: 3 - Alpha
Classifier: Intended Audience :: Developers
Classifier: License :: OSI Approved :: BSD License
Classifier: Natural Language :: English
Classifier: Programming Language :: Python
Classifier: Topic :: Scientific/Engineering :: Artificial Intelligence
